serialized_data_interface/__init__.py
serialized_data_interface/errors.py
serialized_data_interface/events.py
serialized_data_interface/local_sdi.py
serialized_data_interface/relation.py
serialized_data_interface/sdi.py
serialized_data_interface/shims.py
serialized_data_interface/testing.py
serialized_data_interface/utils.py
serialized_data_interface-0.7.0.dist-info/LICENSE
serialized_data_interface-0.7.0.dist-info/METADATA
serialized_data_interface-0.7.0.dist-info/WHEEL
serialized_data_interface-0.7.0.dist-info/RECORD
