Metadata-Version: 2.1
Name: serialized-data-interface
Version: 0.7.0
Summary: Serialized Data Interface for Juju Operators
Home-page: https://github.com/canonical/serialized-data-interface/
License: Apache-2.0
Author: Dominik Fleischmann
Author-email: dominik.fleischmann@canonical.com
Requires-Python: >=3.8,<4.0
Classifier: License :: OSI Approved :: Apache Software License
Classifier: Operating System :: OS Independent
Classifier: Programming Language :: Python :: 3
Classifier: Programming Language :: Python :: 3.8
Classifier: Programming Language :: Python :: 3.9
Classifier: Programming Language :: Python :: 3.10
Classifier: Programming Language :: Python :: 3.11
Requires-Dist: jsonschema (>4,<4.18)
Requires-Dist: ops
Requires-Dist: pyyaml
Requires-Dist: requests
Project-URL: Repository, https://github.com/canonical/serialized-data-interface/
